redis_ext/__about__.py
redis_ext/__init__.py
redis_ext/debounce_task.md
redis_ext/debounce_task.py
redis_ext/fastset.py
redis_ext/py.typed
redis_ext/tasks.py
redis_ext/types.py
redis_ext/unique_id.py
redis_ext/worker.py
redis_ext_ramwin-0.6.1.dist-info/METADATA
redis_ext_ramwin-0.6.1.dist-info/WHEEL
redis_ext_ramwin-0.6.1.dist-info/licenses/LICENSE.txt
redis_ext_ramwin-0.6.1.dist-info/RECORD
