Metadata-Version: 2.4
Name: redis-ext-ramwin
Version: 0.6.1
Summary: Redis list consumer with thread-pool
Project-URL: Homepage, https://github.com/ramwin/redis-ext
Project-URL: Repository, https://github.com/ramwin/redis-ext
License-File: LICENSE.txt
Requires-Python: >=3.8
Requires-Dist: redis>=5.0
Provides-Extra: test
Requires-Dist: fakeredis[lua]; extra == 'test'
Requires-Dist: pytest-cov; extra == 'test'
Requires-Dist: pytest>=7; extra == 'test'
